Metadata-Version: 1.1
Name: kavenegar
Version: 1.1.1
Summary: Kavenegar Python library
Home-page: https://github.com/kavenegar/kavenegar-python
Author: Kavenegar Team
Author-email: support@kavenegar.com
License: UNKNOWN
Keywords: kavenegar,sms
Platform: UNKNOWN
Classifier: Programming Language :: Python
Classifier: Operating System :: OS Independent
Classifier: License :: OSI Approved :: MIT License
Classifier: Intended Audience :: Developers
Classifier: Development Status :: 5 - Production/Stable
Classifier: Topic :: Software Development :: Libraries :: Python Modules
Classifier: Topic :: Communications :: Telephony
